LICENSE
MANIFEST.in
README.md
setup.py
flyplanner/fly.py
flyplanner/fly_plan.py
flyplanner/geom.py
happydevelopperfr_flyplanner.egg-info/PKG-INFO
happydevelopperfr_flyplanner.egg-info/SOURCES.txt
happydevelopperfr_flyplanner.egg-info/dependency_links.txt
happydevelopperfr_flyplanner.egg-info/top_level.txt