Metadata-Version: 1.0
Name: happydevelopperfr-flyplanner
Version: 0.0.7
Summary: fly planner for happy.developper.fr
Home-page: https://github.com/happy-developer-fr/fly-planner
Author: COTTET Julien
Author-email: happy.developper.fr@gmail.com
License: Copyright 2020 COTTET Julien
